[
{
"id": "310029",
"類型": "判決",
"字號": "111憲判15",
"日期": "2022-08-12",
"案由": "聲請人一為審理臺灣雲林地方法院101年度訴字第158號排除侵害事件，認所應適用之中華民國59年2月9日修正公布之農田水利會組織通則第11條第2項前段規定牴觸憲法，裁定停止審判，聲請解釋憲法。聲請人二為補償事務事件，認最高行政法院106年度判字第453號判決，所適用之上開規定有牴觸憲法之疑義，聲請解釋憲法",
"標題": "農田水利用地照舊使用案"
},
{
"id": "325412",
"類型": "判決",
"字號": "111憲判14",
"日期": "2022-08-12",
"案由": "聲請人認農田水利法第1條等規定牴觸憲法，聲請憲法解釋",
"標題": "農田水利會改制案"
},
{
"id": "309956",
"類型": "判決",
"字號": "111憲判13",
"日期": "2022-08-12",
"案由": "聲請人因個人資料保護法事件，認最高行政法院106年度判字第54號判決，所適用之個人資料保護法第6條第1項但書第4款規定等，有違憲疑義，聲請解釋憲法。",
"標題": "健保資料庫案"
},
{
"id": "340615",
"類型": "判決",
"字號": "111憲判12",
"日期": "2022-07-29",
"案由": "聲請人認最高行政法院106年度判字第628號判決所適用之國立臺灣大學法律學院教師評鑑辦法施行細則第5條至第8條規定牴觸憲法，依司法院大法官審理案件法第5條第1項第2款規定，聲請解釋憲法",
"標題": "臺大法律學院教師評鑑案"
},
{
"id": "309958",
"類型": "判決",
"字號": "111憲判11",
"日期": "2022-07-29",
"案由": "聲請人因聘任事件，認最高行政法院中華民國106年6月份第2次庭長法官聯席會議決議，有牴觸憲法之疑義，聲請解釋憲法",
"標題": "公立大學就不續聘教師之再申訴決定提起行政訴訟案"
},
{
"id": "309974",
"類型": "判決",
"字號": "111憲判10",
"日期": "2022-06-24",
"案由": "聲請人認最高行政法院106年度判字第76號判決所適用之警察人員人事條例第31條第1項第11款等規定牴觸憲法，聲請解釋憲法，並聲請補充解釋",
"標題": "警消人員獎懲累積達二大過免職案"
},
{
"id": "339757",
"類型": "判決",
"字號": "111憲判9",
"日期": "2022-06-24",
"案由": "聲請人因審理臺北高等行政法院106年度訴字第936號人事行政事務事件，就應適用之公務人員考績法相關規定，聲請憲法解釋",
"標題": "公務人員考績丁等免職案"
},
{
"id": "340546",
"類型": "判決",
"字號": "111憲判8",
"日期": "2022-05-27",
"案由": "聲請人認最高法院111年度台簡抗字第13號民事確定終局裁定等牴觸憲法，聲請裁判憲法審查",
"標題": "改定親權事件暫時處分案"
},
{
"id": "309994",
"類型": "判決",
"字號": "111憲判7",
"日期": "2022-05-27",
"案由": "聲請人認臺灣高雄地方法院105年度聲字第2531號刑事裁定，所適用之刑事訴訟法第416條第1項等規定，牴觸憲法，聲請解釋憲法",
"標題": "偵查中辯護人在場筆記權等之救濟案"
},
{
"id": "309577",
"類型": "判決",
"字號": "111憲判6",
"日期": "2022-05-13",
"案由": "聲請人一至五分別就其制定食品安全相關之自治條例，經衛生福利部及行政院函告無效及不予核定部分，聲請憲法解釋及統一解釋",
"標題": "萊劑殘留標準之權限爭議案"
},
{
"id": "309913",
"類型": "判決",
"字號": "111憲判5",
"日期": "2022-04-29",
"案由": "聲請人認最高行政法院105年度判字第661號判決所援用之財政部中華民國66年3月9日台財稅第31580號函牴觸憲法，聲請解釋憲法。",
"標題": "營利事業所得跨年度盈虧互抵案"
},
{
"id": "309908",
"類型": "判決",
"字號": "111憲判4",
"日期": "2022-04-01",
"案由": "聲請人為原住民身分法事件，分別認最高行政法院106年度判字第305號、第306號及第752號判決所適用之原住民身分法第4條第2項及中華民國97年12月3日修正公布同法第8條準用第4條第2項規定部分違憲，並分別於107年2月14日及107年10月29日依司法院大法官審理案件法第5條第1項第2款規定聲請解釋憲法，請求宣告法規範違憲。",
"標題": "原住民與非原住民結婚所生子女之原住民身分案"
},
{
"id": "340434",
"類型": "判決",
"字號": "111憲判3",
"日期": "2022-03-25",
"案由": "聲請人認臺灣高等法院109年度偵抗字第1036號刑事確定終局裁定，所適用之刑事訴訟法第403條及第419條規定，有牴觸憲法之疑義，依司法院大法官審理案件法第5條第1項第2款規定，聲請解釋憲法。",
"標題": "被告之辯護人對羈押裁定抗告案"
},
{
"id": "309998",
"類型": "判決",
"字號": "111憲判2",
"日期": "2022-02-25",
"案由": "聲請人一認臺灣高等法院高雄分院103年度上字第138號確定終局民事判決，聲請人二認臺灣高等法院高雄分院104年度上更（一）字第14號確定終局民事判決，聲請人三認臺灣高等法院107年度上字第682號確定終局民事判決，聲請人四認臺灣高等法院108年度重上更一字第164號確定終局民事判決，各所適用之民法第195條第1項後段牴觸憲法，聲請宣告違憲，並聲請變更司法院釋字第656號解釋。",
"標題": "強制道歉案（二）"
},
{
"id": "310024",
"類型": "判決",
"字號": "111憲判1",
"日期": "2022-02-25",
"案由": "聲請人因審理臺灣花蓮地方法院107年度玉原交易字第1號及107年度花原交簡字第403號公共危險案件，認所應適用之中華民國102年1月30日修正公布之道路交通管理處罰條例第35條第5項等規定牴觸憲法，依司法院釋字第371號、第572號及第590號解釋意旨，聲請解釋憲法。",
"標題": "肇事駕駛人受強制抽血檢測酒精濃度案"
},
{
"id": "340360",
"類型": "實體裁定",
"字號": "111憲暫裁1",
"日期": "2022-03-18",
"案由": "聲請人為改定未成年子女權利義務行使負擔等事件之聲請暫時處分事件（最高法院111年度台簡抗字第13號確定終局裁定），聲請裁判憲法審查暨暫時處分"
},
{
"id": "340104",
"類型": "實體裁定",
"字號": "111憲裁57",
"日期": "2022-02-25",
"案由": "聲請人認臺灣高等法院臺中分院94年度上易字第429號刑事判決所適用中華民國81年7月29日修正公布之竊盜犯贓物犯保安處分條例第3條第1項及第5條第1項前段規定違憲，依司法院大法官審理案件法第5條第1項第2款規定聲請解釋。"
}
]